{
  "uid": "an5.162",
  "title": "Dutiyaāghātapaṭivinayasutta",
  "nikaya": "an",
  "segments": [
    {
      "id": "an5.162:1.1",
      "pali": "Tatra kho āyasmā sāriputto bhikkhū āmantesi:"
    },
    {
      "id": "an5.162:1.2",
      "pali": "“āvuso bhikkhave”ti."
    },
    {
      "id": "an5.162:1.3",
      "pali": "“Āvuso”ti kho te bhikkhū āyasmato sāriputtassa paccassosuṁ."
    },
    {
      "id": "an5.162:1.4",
      "pali": "Āyasmā sāriputto etadavoca:"
    },
    {
      "id": "an5.162:2.1",
      "pali": "“Pañcime, āvuso, āghātapaṭivinayā yattha bhikkhuno uppanno āghāto sabbaso paṭivinetabbo."
    },
    {
      "id": "an5.162:2.2",
      "pali": "Katame pañca?"
    },
    {
      "id": "an5.162:2.3",
      "pali": "Idhāvuso, ekacco puggalo aparisuddhakāyasamācāro hoti parisuddhavacīsamācāro;"
    },
    {
      "id": "an5.162:2.4",
      "pali": "evarūpepi, āvuso, puggale āghāto paṭivinetabbo."
    },
    {
      "id": "an5.162:2.5",
      "pali": "Idha panāvuso, ekacco puggalo aparisuddhavacīsamācāro hoti parisuddhakāyasamācāro;"
    },
    {
      "id": "an5.162:2.6",
      "pali": "evarūpepi, āvuso, puggale āghāto paṭivinetabbo."
    },
    {
      "id": "an5.162:2.7",
      "pali": "Idha panāvuso, ekacco puggalo aparisuddhakāyasamācāro hoti aparisuddhavacīsamācāro, labhati ca kālena kālaṁ cetaso vivaraṁ cetaso pasādaṁ;"
    },
    {
      "id": "an5.162:2.8",
      "pali": "evarūpepi, āvuso, puggale āghāto paṭivinetabbo."
    },
    {
      "id": "an5.162:2.9",
      "pali": "Idha panāvuso, ekacco puggalo aparisuddhakāyasamācāro hoti aparisuddhavacīsamācāro, na ca labhati kālena kālaṁ cetaso vivaraṁ cetaso pasādaṁ;"
    },
    {
      "id": "an5.162:2.10",
      "pali": "evarūpepi, āvuso, puggale āghāto paṭivinetabbo."
    },
    {
      "id": "an5.162:2.11",
      "pali": "Idha panāvuso, ekacco puggalo parisuddhakāyasamācāro parisuddhavacīsamācāro, labhati ca kālena vā kālaṁ cetaso vivaraṁ cetaso pasādaṁ;"
    },
    {
      "id": "an5.162:2.12",
      "pali": "evarūpepi, āvuso, puggale āghāto paṭivinetabbo."
    },
    {
      "id": "an5.162:3.1",
      "pali": "Tatrāvuso, yvāyaṁ puggalo aparisuddhakāyasamācāro parisuddhavacīsamācāro, kathaṁ tasmiṁ puggale āghāto paṭivinetabbo?"
    },
    {
      "id": "an5.162:3.2",
      "pali": "Seyyathāpi, āvuso, bhikkhu paṁsukūliko rathiyāya nantakaṁ disvā vāmena pādena niggaṇhitvā dakkhiṇena pādena pattharitvā, yo tattha sāro taṁ paripātetvā ādāya pakkameyya;"
    },
    {
      "id": "an5.162:3.3",
      "pali": "evamevaṁ khvāvuso, yvāyaṁ puggalo aparisuddhakāyasamācāro parisuddhavacīsamācāro, yāssa aparisuddhakāyasamācāratā na sāssa tasmiṁ samaye manasi kātabbā, yā ca khvassa parisuddhavacīsamācāratā sāssa tasmiṁ samaye manasi kātabbā."
    },
    {
      "id": "an5.162:3.4",
      "pali": "Evaṁ tasmiṁ puggale āghāto paṭivinetabbo."
    },
    {
      "id": "an5.162:4.1",
      "pali": "Tatrāvuso, yvāyaṁ puggalo aparisuddhavacīsamācāro parisuddhakāyasamācāro, kathaṁ tasmiṁ puggale āghāto paṭivinetabbo?"
    },
    {
      "id": "an5.162:4.2",
      "pali": "Seyyathāpi, āvuso, pokkharaṇī sevālapaṇakapariyonaddhā."
    },
    {
      "id": "an5.162:4.3",
      "pali": "Atha puriso āgaccheyya ghammābhitatto ghammapareto kilanto tasito pipāsito."
    },
    {
      "id": "an5.162:4.4",
      "pali": "So taṁ pokkharaṇiṁ ogāhetvā ubhohi hatthehi iticiti ca sevālapaṇakaṁ apaviyūhitvā añjalinā pivitvā pakkameyya."
    },
    {
      "id": "an5.162:4.5",
      "pali": "Evamevaṁ kho, āvuso, yvāyaṁ puggalo aparisuddhavacīsamācāro parisuddhakāyasamācāro, yāssa aparisuddhavacīsamācāratā na sāssa tasmiṁ samaye manasi kātabbā, yā ca khvassa parisuddhakāyasamācāratā sāssa tasmiṁ samaye manasi kātabbā."
    },
    {
      "id": "an5.162:4.6",
      "pali": "Evaṁ tasmiṁ puggale āghāto paṭivinetabbo."
    },
    {
      "id": "an5.162:5.1",
      "pali": "Tatrāvuso, yvāyaṁ puggalo aparisuddhakāyasamācāro aparisuddhavacīsamācāro labhati ca kālena kālaṁ cetaso vivaraṁ cetaso pasādaṁ, kathaṁ tasmiṁ puggale āghāto paṭivinetabbo?"
    },
    {
      "id": "an5.162:5.2",
      "pali": "Seyyathāpi, āvuso, parittaṁ gopade udakaṁ."
    },
    {
      "id": "an5.162:5.3",
      "pali": "Atha puriso āgaccheyya ghammābhitatto ghammapareto kilanto tasito pipāsito."
    },
    {
      "id": "an5.162:5.4",
      "pali": "Tassa evamassa:"
    },
    {
      "id": "an5.162:5.5",
      "pali": "‘idaṁ kho parittaṁ gopade udakaṁ."
    },
    {
      "id": "an5.162:5.6",
      "pali": "Sacāhaṁ añjalinā vā pivissāmi bhājanena vā khobhessāmipi taṁ loḷessāmipi taṁ apeyyampi taṁ karissāmi."
    },
    {
      "id": "an5.162:5.7",
      "pali": "Yannūnāhaṁ catukkuṇḍiko nipatitvā gopītakaṁ pivitvā pakkameyyan’ti."
    },
    {
      "id": "an5.162:5.8",
      "pali": "So catukkuṇḍiko nipatitvā gopītakaṁ pivitvā pakkameyya."
    },
    {
      "id": "an5.162:5.9",
      "pali": "Evamevaṁ kho, āvuso, yvāyaṁ puggalo aparisuddhakāyasamācāro aparisuddhavacīsamācāro labhati ca kālena kālaṁ cetaso vivaraṁ cetaso pasādaṁ, yāssa aparisuddhakāyasamācāratā na sāssa tasmiṁ samaye manasi kātabbā;"
    },
    {
      "id": "an5.162:5.10",
      "pali": "yāpissa aparisuddhavacīsamācāratā na sāpissa tasmiṁ samaye manasi kātabbā."
    },
    {
      "id": "an5.162:5.11",
      "pali": "Yañca kho so labhati kālena kālaṁ cetaso vivaraṁ cetaso pasādaṁ, tamevassa tasmiṁ samaye manasi kātabbaṁ."
    },
    {
      "id": "an5.162:5.12",
      "pali": "Evaṁ tasmiṁ puggale āghāto paṭivinetabbo."
    },
    {
      "id": "an5.162:6.1",
      "pali": "Tatrāvuso, yvāyaṁ puggalo aparisuddhakāyasamācāro aparisuddhavacīsamācāro na ca labhati kālena kālaṁ cetaso vivaraṁ cetaso pasādaṁ, kathaṁ tasmiṁ puggale āghāto paṭivinetabbo?"
    },
    {
      "id": "an5.162:6.2",
      "pali": "Seyyathāpi, āvuso, puriso ābādhiko dukkhito bāḷhagilāno addhānamaggappaṭipanno."
    },
    {
      "id": "an5.162:6.3",
      "pali": "Tassa puratopissa dūre gāmo pacchatopissa dūre gāmo."
    },
    {
      "id": "an5.162:6.4",
      "pali": "So na labheyya sappāyāni bhojanāni, na labheyya sappāyāni bhesajjāni, na labheyya patirūpaṁ upaṭṭhākaṁ, na labheyya gāmantanāyakaṁ."
    },
    {
      "id": "an5.162:6.5",
      "pali": "Tamenaṁ aññataro puriso passeyya addhānamaggappaṭipanno."
    },
    {
      "id": "an5.162:6.6",
      "pali": "So tasmiṁ purise kāruññaṁyeva upaṭṭhāpeyya, anuddayaṁyeva upaṭṭhāpeyya, anukampaṁyeva upaṭṭhāpeyya:"
    },
    {
      "id": "an5.162:6.7",
      "pali": "‘aho vatāyaṁ puriso labheyya sappāyāni bhojanāni, labheyya sappāyāni bhesajjāni, labheyya patirūpaṁ upaṭṭhākaṁ, labheyya gāmantanāyakaṁ."
    },
    {
      "id": "an5.162:6.8",
      "pali": "Taṁ kissa hetu?"
    },
    {
      "id": "an5.162:6.9",
      "pali": "Māyaṁ puriso idheva anayabyasanaṁ āpajjī’ti."
    },
    {
      "id": "an5.162:6.10",
      "pali": "Evamevaṁ kho, āvuso, yvāyaṁ puggalo aparisuddhakāyasamācāro aparisuddhavacīsamācāro na ca labhati kālena kālaṁ cetaso vivaraṁ cetaso pasādaṁ, evarūpepi, āvuso, puggale kāruññaṁyeva upaṭṭhāpetabbaṁ anuddayāyeva upaṭṭhāpetabbā anukampāyeva upaṭṭhāpetabbā:"
    },
    {
      "id": "an5.162:6.11",
      "pali": "‘aho vata ayamāyasmā kāyaduccaritaṁ pahāya kāyasucaritaṁ bhāveyya, vacīduccaritaṁ pahāya vacīsucaritaṁ bhāveyya, manoduccaritaṁ pahāya manosucaritaṁ bhāveyya."
    },
    {
      "id": "an5.162:6.12",
      "pali": "Taṁ kissa hetu?"
    },
    {
      "id": "an5.162:6.13",
      "pali": "Māyaṁ āyasmā kāyassa bhedā paraṁ maraṇā apāyaṁ duggatiṁ vinipātaṁ nirayaṁ upapajjī’ti."
    },
    {
      "id": "an5.162:6.14",
      "pali": "Evaṁ tasmiṁ puggale āghāto paṭivinetabbo."
    },
    {
      "id": "an5.162:7.1",
      "pali": "Tatrāvuso, yvāyaṁ puggalo parisuddhakāyasamācāro parisuddhavacīsamācāro labhati ca kālena kālaṁ cetaso vivaraṁ cetaso pasādaṁ, kathaṁ tasmiṁ puggale āghāto paṭivinetabbo?"
    },
    {
      "id": "an5.162:7.2",
      "pali": "Seyyathāpi, āvuso, pokkharaṇī acchodakā sātodakā sītodakā setakā supatitthā ramaṇīyā nānārukkhehi sañchannā."
    },
    {
      "id": "an5.162:7.3",
      "pali": "Atha puriso āgaccheyya ghammābhitatto ghammapareto kilanto tasito pipāsito."
    },
    {
      "id": "an5.162:7.4",
      "pali": "So taṁ pokkharaṇiṁ ogāhetvā nhātvā ca pivitvā ca paccuttaritvā tattheva rukkhacchāyāya nisīdeyya vā nipajjeyya vā."
    },
    {
      "id": "an5.162:8.1",
      "pali": "Evamevaṁ kho, āvuso, yvāyaṁ puggalo parisuddhakāyasamācāro parisuddhavacīsamācāro labhati ca kālena kālaṁ cetaso vivaraṁ cetaso pasādaṁ, yāpissa parisuddhakāyasamācāratā sāpissa tasmiṁ samaye manasi kātabbā;"
    },
    {
      "id": "an5.162:8.2",
      "pali": "yāpissa parisuddhavacīsamācāratā sāpissa tasmiṁ samaye manasi kātabbā;"
    },
    {
      "id": "an5.162:8.3",
      "pali": "yampi labhati kālena kālaṁ cetaso vivaraṁ cetaso pasādaṁ, tampissa tasmiṁ samaye manasi kātabbaṁ."
    },
    {
      "id": "an5.162:8.4",
      "pali": "Evaṁ tasmiṁ puggale āghāto paṭivinetabbo."
    },
    {
      "id": "an5.162:8.5",
      "pali": "Samantapāsādikaṁ, āvuso, puggalaṁ āgamma cittaṁ pasīdati."
    },
    {
      "id": "an5.162:9.1",
      "pali": "Ime kho, āvuso, pañca āghātapaṭivinayā, yattha bhikkhuno uppanno āghāto sabbaso paṭivinetabbo”ti."
    },
    {
      "id": "an5.162:9.2",
      "pali": "Dutiyaṁ."
    }
  ]
}
