{
  "uid": "an5.132",
  "title": "Dutiyacakkānuvattanasutta",
  "nikaya": "an",
  "segments": [
    {
      "id": "an5.132:1.1",
      "pali": "“Pañcahi, bhikkhave, aṅgehi samannāgato rañño cakkavattissa jeṭṭho putto pitarā pavattitaṁ cakkaṁ dhammeneva anuppavatteti;"
    },
    {
      "id": "an5.132:1.2",
      "pali": "taṁ hoti cakkaṁ appaṭivattiyaṁ kenaci manussabhūtena paccatthikena pāṇinā."
    },
    {
      "id": "an5.132:2.1",
      "pali": "Katamehi pañcahi?"
    },
    {
      "id": "an5.132:2.2",
      "pali": "Idha, bhikkhave, rañño cakkavattissa jeṭṭho putto atthaññū ca hoti, dhammaññū ca, mattaññū ca, kālaññū ca, parisaññū ca."
    },
    {
      "id": "an5.132:2.3",
      "pali": "Imehi kho, bhikkhave, pañcahi aṅgehi samannāgato rañño cakkavattissa jeṭṭho putto pitarā pavattitaṁ cakkaṁ dhammeneva anuppavatteti;"
    },
    {
      "id": "an5.132:2.4",
      "pali": "taṁ hoti cakkaṁ appaṭivattiyaṁ kenaci manussabhūtena paccatthikena pāṇinā."
    },
    {
      "id": "an5.132:3.1",
      "pali": "Evamevaṁ kho, bhikkhave, pañcahi dhammehi samannāgato sāriputto tathāgatena anuttaraṁ dhammacakkaṁ pavattitaṁ sammadeva anuppavatteti;"
    },
    {
      "id": "an5.132:3.2",
      "pali": "taṁ hoti cakkaṁ appaṭivattiyaṁ samaṇena vā brāhmaṇena vā devena vā mārena vā brahmunā vā kenaci vā lokasmiṁ."
    },
    {
      "id": "an5.132:4.1",
      "pali": "Katamehi pañcahi?"
    },
    {
      "id": "an5.132:4.2",
      "pali": "Idha, bhikkhave, sāriputto atthaññū, dhammaññū, mattaññū, kālaññū, parisaññū."
    },
    {
      "id": "an5.132:4.3",
      "pali": "Imehi kho, bhikkhave, pañcahi dhammehi samannāgato sāriputto tathāgatena anuttaraṁ dhammacakkaṁ pavattitaṁ sammadeva anuppavatteti;"
    },
    {
      "id": "an5.132:4.4",
      "pali": "taṁ hoti cakkaṁ appaṭivattiyaṁ samaṇena vā brāhmaṇena vā devena vā mārena vā brahmunā vā kenaci vā lokasmin”ti."
    },
    {
      "id": "an5.132:4.5",
      "pali": "Dutiyaṁ."
    }
  ]
}
