{
  "uid": "ud2.9",
  "title": "Visākhāsutta",
  "nikaya": "kn",
  "segments": [
    {
      "id": "ud2.9:1.1",
      "pali": "Evaṁ me sutaṁ—"
    },
    {
      "id": "ud2.9:1.2",
      "pali": "ekaṁ samayaṁ bhagavā sāvatthiyaṁ viharati pubbārāme migāramātupāsāde."
    },
    {
      "id": "ud2.9:1.3",
      "pali": "Tena kho pana samayena visākhāya migāramātuyā kocideva attho raññe pasenadimhi kosale paṭibaddho hoti."
    },
    {
      "id": "ud2.9:1.4",
      "pali": "Taṁ rājā pasenadi kosalo na yathādhippāyaṁ tīreti."
    },
    {
      "id": "ud2.9:2.1",
      "pali": "Atha kho visākhā migāramātā divā divassa yena bhagavā tenupasaṅkami; upasaṅkamitvā bhagavantaṁ abhivādetvā ekamantaṁ nisīdi."
    },
    {
      "id": "ud2.9:2.2",
      "pali": "Ekamantaṁ nisinnaṁ kho visākhaṁ migāramātaraṁ bhagavā etadavoca:"
    },
    {
      "id": "ud2.9:2.3",
      "pali": "“handa kuto nu tvaṁ, visākhe, āgacchasi divā divassā”ti?"
    },
    {
      "id": "ud2.9:2.4",
      "pali": "“Idha me, bhante, kocideva attho raññe pasenadimhi kosale paṭibaddho;"
    },
    {
      "id": "ud2.9:2.5",
      "pali": "taṁ rājā pasenadi kosalo na yathādhippāyaṁ tīretī”ti."
    },
    {
      "id": "ud2.9:3.1",
      "pali": "Atha kho bhagavā etamatthaṁ viditvā tāyaṁ velāyaṁ imaṁ udānaṁ udānesi:"
    },
    {
      "id": "ud2.9:4.1",
      "pali": "“Sabbaṁ paravasaṁ dukkhaṁ,"
    },
    {
      "id": "ud2.9:4.2",
      "pali": "sabbaṁ issariyaṁ sukhaṁ;"
    },
    {
      "id": "ud2.9:4.3",
      "pali": "Sādhāraṇe vihaññanti,"
    },
    {
      "id": "ud2.9:4.4",
      "pali": "yogā hi duratikkamā”ti."
    },
    {
      "id": "ud2.9:4.5",
      "pali": "Navamaṁ."
    }
  ]
}
