{
  "uid": "sn15.3",
  "title": "Assusutta",
  "nikaya": "sn",
  "segments": [
    {
      "id": "sn15.3:1.1",
      "pali": "Sāvatthiyaṁ viharati."
    },
    {
      "id": "sn15.3:1.2",
      "pali": "“Anamataggoyaṁ, bhikkhave, saṁsāro."
    },
    {
      "id": "sn15.3:1.3",
      "pali": "Pubbā koṭi na paññāyati avijjānīvaraṇānaṁ sattānaṁ taṇhāsaṁyojanānaṁ sandhāvataṁ saṁsarataṁ."
    },
    {
      "id": "sn15.3:1.4",
      "pali": "Taṁ kiṁ maññatha, bhikkhave, katamaṁ nu kho bahutaraṁ, yaṁ vā vo iminā dīghena addhunā sandhāvataṁ saṁsarataṁ amanāpasampayogā manāpavippayogā kandantānaṁ rodantānaṁ assu passannaṁ paggharitaṁ, yaṁ vā catūsu mahāsamuddesu udakan”ti?"
    },
    {
      "id": "sn15.3:1.5",
      "pali": "“Yathā kho mayaṁ, bhante, bhagavatā dhammaṁ desitaṁ ājānāma, etadeva, bhante, bahutaraṁ yaṁ no iminā dīghena addhunā sandhāvataṁ saṁsarataṁ amanāpasampayogā manāpavippayogā kandantānaṁ rodantānaṁ assu passannaṁ paggharitaṁ, na tveva catūsu mahāsamuddesu udakan”ti."
    },
    {
      "id": "sn15.3:2.1",
      "pali": "“Sādhu sādhu, bhikkhave, sādhu kho me tumhe, bhikkhave, evaṁ dhammaṁ desitaṁ ājānātha."
    },
    {
      "id": "sn15.3:2.2",
      "pali": "Etadeva, bhikkhave, bahutaraṁ yaṁ vo iminā dīghena addhunā sandhāvataṁ saṁsarataṁ amanāpasampayogā manāpavippayogā kandantānaṁ rodantānaṁ assu passannaṁ paggharitaṁ, na tveva catūsu mahāsamuddesu udakaṁ."
    },
    {
      "id": "sn15.3:2.3",
      "pali": "Dīgharattaṁ vo, bhikkhave, mātumaraṇaṁ paccanubhūtaṁ;"
    },
    {
      "id": "sn15.3:2.4",
      "pali": "tesaṁ vo mātumaraṇaṁ paccanubhontānaṁ amanāpasampayogā manāpavippayogā kandantānaṁ rodantānaṁ assu passannaṁ paggharitaṁ, na tveva catūsu mahāsamuddesu udakaṁ."
    },
    {
      "id": "sn15.3:2.5",
      "pali": "Dīgharattaṁ vo, bhikkhave, pitumaraṇaṁ paccanubhūtaṁ …pe…"
    },
    {
      "id": "sn15.3:2.6",
      "pali": "bhātumaraṇaṁ paccanubhūtaṁ …"
    },
    {
      "id": "sn15.3:2.7",
      "pali": "bhaginimaraṇaṁ paccanubhūtaṁ …"
    },
    {
      "id": "sn15.3:2.8",
      "pali": "puttamaraṇaṁ paccanubhūtaṁ …"
    },
    {
      "id": "sn15.3:2.9",
      "pali": "dhītumaraṇaṁ paccanubhūtaṁ …"
    },
    {
      "id": "sn15.3:2.10",
      "pali": "ñātibyasanaṁ paccanubhūtaṁ …"
    },
    {
      "id": "sn15.3:2.11",
      "pali": "bhogabyasanaṁ paccanubhūtaṁ."
    },
    {
      "id": "sn15.3:2.12",
      "pali": "Dīgharattaṁ vo, bhikkhave, rogabyasanaṁ paccanubhūtaṁ, tesaṁ vo rogabyasanaṁ paccanubhontānaṁ amanāpasampayogā manāpavippayogā kandantānaṁ rodantānaṁ assu passannaṁ paggharitaṁ, na tveva catūsu mahāsamuddesu udakaṁ."
    },
    {
      "id": "sn15.3:2.13",
      "pali": "Taṁ kissa hetu?"
    },
    {
      "id": "sn15.3:2.14",
      "pali": "Anamataggoyaṁ, bhikkhave, saṁsāro …pe…"
    },
    {
      "id": "sn15.3:2.15",
      "pali": "yāvañcidaṁ, bhikkhave, alameva sabbasaṅkhāresu nibbindituṁ, alaṁ virajjituṁ, alaṁ vimuccitun”ti."
    },
    {
      "id": "sn15.3:2.16",
      "pali": "Tatiyaṁ."
    }
  ]
}
